pytest_stepwise/__init__.py
pytest_stepwise/compat.py
pytest_stepwise/plugin.py
pytest_stepwise-0.4.dist-info/DESCRIPTION.rst
pytest_stepwise-0.4.dist-info/METADATA
pytest_stepwise-0.4.dist-info/RECORD
pytest_stepwise-0.4.dist-info/WHEEL
pytest_stepwise-0.4.dist-info/entry_points.txt
pytest_stepwise-0.4.dist-info/metadata.json
pytest_stepwise-0.4.dist-info/top_level.txt
