Metadata-Version: 2.0
Name: pytest-stepwise
Version: 0.4
Summary: Run a test suite one failing test at a time.
Home-page: https://github.com/nip3o/pytest-stepwise
Author: Niclas Olofsson
Author-email: n@niclasolofsson.se
License: MIT
Platform: UNKNOWN
Classifier: Development Status :: 4 - Beta
Classifier: Intended Audience :: Developers
Classifier: Topic :: Software Development :: Testing
Classifier: Programming Language :: Python
Classifier: Operating System :: OS Independent
Classifier: License :: OSI Approved :: MIT License
Requires-Dist: pytest (>=2.2)
